simple_python_profiler/__init__.py
simple_python_profiler/__main__.py
simple_python_profiler/main.py
simple_python_profiler/tests.py
simple_python_profiler-0.2.dist-info/WHEEL
simple_python_profiler-0.2.dist-info/METADATA
simple_python_profiler-0.2.dist-info/RECORD
